[
    {
        "title": "aku mau tidur",
        "complete": false,
        "tags": [
            "bantal",
            "guling"
        ]
    },
    {
        "title": "aku mau makan",
        "complete": true,
        "tags": [
            "lauk",
            "cimol"
        ]
    },
    {
        "title": "aku mau jajan",
        "complete": true,
        "tags": [
            "seblak",
            "cimol",
            "cendol",
            "yakult"
        ]
    },
    {
        "title": "futsal dulu",
        "complete": true,
        "tags": []
    }
]